aef_gw/__init__.py
aef_gw/aef_gw.py
aef_gw/cli.py
aef_gw-0.1.15.dist-info/METADATA
aef_gw-0.1.15.dist-info/WHEEL
aef_gw-0.1.15.dist-info/entry_points.txt
aef_gw-0.1.15.dist-info/top_level.txt
aef_gw-0.1.15.dist-info/RECORD
