Metadata-Version: 2.1
Name: aef_gw
Version: 0.1.15
Summary: AEF_GW is a component designed to facilitate the integration of legacy systems with the Common API Framework (CAPIF).
Home-page: https://github.com/Telefonica/pesp_aef_gw
Author: JorgeEcheva
Author-email: jorge.echevarriauribarri.practicas@telefonica.com
Classifier: Programming Language :: Python :: 3
Classifier: Operating System :: OS Independent
Requires-Python: >=3.9
Requires-Dist: annotated-types==0.7.0
Requires-Dist: anyio==4.6.2.post1
Requires-Dist: arrow==1.3.0
Requires-Dist: binaryornot==0.4.4
Requires-Dist: blinker==1.9.0
Requires-Dist: certifi==2024.7.4
Requires-Dist: cffi==1.17.1
Requires-Dist: chardet==5.2.0
Requires-Dist: charset-normalizer==3.4.0
Requires-Dist: click==8.1.7
Requires-Dist: coverage==4.5.4
Requires-Dist: cryptography==38.0.4
Requires-Dist: ecdsa==0.19.0
Requires-Dist: fastapi==0.115.5
Requires-Dist: flake8==3.9.2
Requires-Dist: Flask==3.0.3
Requires-Dist: Flask-JWT-Extended==4.6.0
Requires-Dist: h11==0.14.0
Requires-Dist: idna==3.7
Requires-Dist: iniconfig==2.0.0
Requires-Dist: itsdangerous==2.2.0
Requires-Dist: Jinja2==3.1.4
Requires-Dist: jinja2-time==0.2.0
Requires-Dist: MarkupSafe==2.1.5
Requires-Dist: mccabe==0.6.1
Requires-Dist: opencapif_sdk==0.1.15
Requires-Dist: packaging==24.2
Requires-Dist: pip==24.0
Requires-Dist: pluggy==1.5.0
Requires-Dist: pyasn1==0.6.1
Requires-Dist: pycodestyle==2.7.0
Requires-Dist: pycparser==2.22
Requires-Dist: pydantic==2.10.0
Requires-Dist: pydantic_core==2.27.0
Requires-Dist: pyflakes==2.3.1
Requires-Dist: PyJWT==2.10.0
Requires-Dist: pyOpenSSL==22.1.0
Requires-Dist: pytest==8.3.2
Requires-Dist: python-dateutil==2.9.0.post0
Requires-Dist: python-jose==3.3.0
Requires-Dist: PyYAML==6.0.1
Requires-Dist: requests==2.32.3
Requires-Dist: rsa==4.9
Requires-Dist: six==1.16.0
Requires-Dist: sniffio==1.3.1
Requires-Dist: starlette==0.41.3
Requires-Dist: text-unidecode==1.3
Requires-Dist: types-python-dateutil==2.9.0.20241003
Requires-Dist: urllib3==2.2.2
Requires-Dist: uvicorn==0.32.1
Requires-Dist: Werkzeug==3.0.4
